Metadata-Version: 1.1
Name: drf-authentication
Version: 0.1.0
Summary: Django Rest Framework Authentication Module with Angular
Home-page: https://github.com/cenkbircanoglu/drf_authentication
Author: Cenk Bircanoglu
Author-email: cenk.bircanoglu@gmail.com
License: MIT
Download-URL: https://github.com/cenkbircanoglu/drf_authentication/tarball/0.1.0
Keywords: django,auth,rest,angular,login,logput,passwordpython
Platform: any
